bitssh/__init__.py
bitssh/__main__.py
bitssh/argument_parser.py
bitssh/cli.py
bitssh/prompt.py
bitssh/py.typed
bitssh/ui.py
bitssh/utils.py
bitssh-3.5.0.dist-info/licenses/LICENSE
bitssh-3.5.0.dist-info/METADATA
bitssh-3.5.0.dist-info/WHEEL
bitssh-3.5.0.dist-info/entry_points.txt
bitssh-3.5.0.dist-info/top_level.txt
bitssh-3.5.0.dist-info/RECORD
