Metadata-Version: 2.4
Name: bitssh
Version: 3.5.0
Summary: A new and modern SSH connector written in Python.
Author-email: Kanishk Pachauri <itskanishkp.py@gmail.com>
License: MIT
Project-URL: Homepage, https://github.com/Mr-Sunglasses/bitssh
Project-URL: Documentation, https://github.com/Mr-Sunglasses/bitssh/blob/master/docs/docs.md
Project-URL: Repository, https://github.com/Mr-Sunglasses/bitssh
Project-URL: Issues, https://github.com/Mr-Sunglasses/bitssh/issues
Keywords: bitssh,sshmanager,commandline,cli,ssh
Classifier: Intended Audience :: Developers
Classifier: License :: OSI Approved :: MIT License
Classifier: Programming Language :: Python
Classifier: Programming Language :: Python :: 3
Classifier: Programming Language :: Python :: 3.9
Classifier: Programming Language :: Python :: 3.10
Classifier: Programming Language :: Python :: 3.11
Classifier: Programming Language :: Python :: 3.12
Classifier: Programming Language :: Python :: 3.13
Classifier: Environment :: Console
Classifier: Topic :: System :: Shells
Classifier: Topic :: Terminals
Requires-Python: >=3.9
License-File: LICENSE
Requires-Dist: rich>=14.0.0
Requires-Dist: InquirerPy>=0.3.4
Provides-Extra: dev
Requires-Dist: black; extra == "dev"
Requires-Dist: bumpver; extra == "dev"
Requires-Dist: isort; extra == "dev"
Requires-Dist: pytest; extra == "dev"
Dynamic: license-file
